mle_ons_hidrological/__init__.py
mle_ons_hidrological-0.0.1.dist-info/METADATA
mle_ons_hidrological-0.0.1.dist-info/WHEEL
mle_ons_hidrological-0.0.1.dist-info/top_level.txt
mle_ons_hidrological-0.0.1.dist-info/RECORD
